{
  "employees": [
    {
      "employee_name": "yogesh",
      "employee_age": "12",
      "employee_salary": "1111",
      "department": [],
      "id": 2
    },
    {
      "employee_name": "yogesh",
      "employee_age": "12",
      "employee_salary": "1111",
      "department": [
        {
          "dept": "Service",
          "selected": true
        },
        {
          "dept": "Finance",
          "selected": true
        }
      ],
      "id": 3
    },
    {
      "employee_name": "yogesh",
      "employee_age": "12",
      "employee_salary": "1111",
      "department": [
        {
          "dept": "Service",
          "selected": true
        }
      ],
      "statusNow": "confirm",
      "address": {
        "street": "ffff",
        "city": "ffff",
        "state": "ffff",
        "zip": "fff"
      },
      "id": 4
    },
    {
      "employee_name": "yogesh",
      "employee_age": "12",
      "employee_salary": "1111",
      "department": [
        {
          "dept": "Service",
          "selected": true
        }
      ],
      "statusNow": "confirm",
      "address": {
        "street": "rrr",
        "city": "rrr",
        "state": "rrr",
        "zip": "rrr"
      },
      "id": 5
    },
    {
      "employee_name": "test",
      "employee_age": "35",
      "employee_salary": "26000",
      "department": [
        {
          "dept": "Service",
          "selected": true
        }
      ],
      "address": {
        "street": "ffff",
        "city": "ffff",
        "state": "ffff",
        "zip": "fff"
      },
      "id": 6
    },
    {
      "employee_name": "test",
      "employee_age": "12",
      "employee_salary": "1111",
      "department": [
        {
          "dept": "Service",
          "selected": true
        }
      ],
      "address": {
        "street": "ffff",
        "city": "ffff",
        "state": "ffff",
        "zip": "fff"
      },
      "id": 7
    },
    {
      "employee_name": "test",
      "employee_age": "12",
      "employee_salary": "1111",
      "department": [
        {
          "dept": "Service",
          "selected": true
        }
      ],
      "statusNow": "confirm",
      "address": {
        "street": "ffff",
        "city": "ffff",
        "state": "ffff",
        "zip": "fff"
      },
      "id": 8
    }
  ]
}